LinAlgLib/__init__.py
LinAlgLib/functions.py
LinAlgLib-0.1.1.dist-info/METADATA
LinAlgLib-0.1.1.dist-info/WHEEL
LinAlgLib-0.1.1.dist-info/top_level.txt
LinAlgLib-0.1.1.dist-info/RECORD
