Metadata-Version: 2.1
Name: LinAlgLib
Version: 0.1.1
Home-page: https://github.com/DWasilewski3/LinAlgLib
Author: David_Wasilewski
Classifier: License :: OSI Approved :: Python Software Foundation License
Requires-Dist: numpy
Requires-Dist: sympy
